fetch_papers/__init__.py
fetch_papers/affiliation.py
fetch_papers/cli.py
fetch_papers/data/query_corpus.json
fetch_papers/data/tfidf_model.pkl
fetch_papers/main.py
fetch_papers/pubmed.py
fetch_papers/query_suggestions.py
fetch_papers_nishi-0.1.4.dist-info/entry_points.txt
fetch_papers_nishi-0.1.4.dist-info/LICENSE
fetch_papers_nishi-0.1.4.dist-info/METADATA
fetch_papers_nishi-0.1.4.dist-info/WHEEL
fetch_papers_nishi-0.1.4.dist-info/RECORD
