Metadata-Version: 2.3
Name: fetch-papers-nishi
Version: 0.1.4
Summary: A CLI tool to fetch research papers from PubMed with author affiliation filtering
Keywords: pubmed,research,papers,pharmaceutical,biotech
Author: Nishi Chaudhary
Author-email: nishichaudhary2001@gmail.com
Requires-Python: >=3.9,<3.14
Classifier: Development Status :: 4 - Beta
Classifier: Environment :: Console
Classifier: Intended Audience :: Science/Research
Classifier: License :: OSI Approved :: MIT License
Classifier: Programming Language :: Python :: 3
Classifier: Programming Language :: Python :: 3.9
Classifier: Programming Language :: Python :: 3.10
Classifier: Programming Language :: Python :: 3.11
Classifier: Programming Language :: Python :: 3.12
Classifier: Programming Language :: Python :: 3.13
Classifier: Topic :: Scientific/Engineering :: Bio-Informatics
Classifier: Topic :: Scientific/Engineering :: Medical Science Apps.
Requires-Dist: biopython (>=1.81,<2.0)
Requires-Dist: click (>=8.1.3,<9.0.0)
Requires-Dist: flask (>=3.1.0,<4.0.0)
Requires-Dist: flask-login (>=0.6.3,<0.7.0)
Requires-Dist: flask-wtf (>=1.2.2,<2.0.0)
Requires-Dist: gunicorn (>=23.0.0,<24.0.0)
Requires-Dist: pandas (>=2.0.0,<3.0.0)
Requires-Dist: pyinstaller (>=6.12.0,<7.0.0)
Requires-Dist: scikit-learn (>=1.6.1,<2.0.0)
Requires-Dist: tabulate (>=0.9.0,<0.10.0)
Requires-Dist: tqdm (>=4.65.0,<5.0.0)
Project-URL: Homepage, https://github.com/nchaudhary12/PubMed-Research-Paper
Project-URL: Repository, https://github.com/nchaudhary12/PubMed-Research-Paper
